lmso_algorithm/__init__.py
lmso_algorithm/algorithm.py
lmso_algorithm/common.py
lmso_algorithm/echoproc.py
lmso_algorithm-1.2.dist-info/LICENSE
lmso_algorithm-1.2.dist-info/METADATA
lmso_algorithm-1.2.dist-info/WHEEL
lmso_algorithm-1.2.dist-info/top_level.txt
lmso_algorithm-1.2.dist-info/RECORD
