Metadata-Version: 2.1
Name: lmso-algorithm
Version: 1.2
Summary: An Optimized LMS Algorithm
Home-page: https://github.com/alexgrusu/lmso_algorithm
Author: Alexandru - George Rusu
Author-email: aqrusu@gmail.com
License: GPLv3+
Keywords: Adaptive filters,Echo cancellation,System identification
Platform: UNKNOWN
Classifier: Development Status :: 6 - Mature
Classifier: Intended Audience :: Science/Research
Classifier: Natural Language :: English
Classifier: License :: OSI Approved :: GNU General Public License v3 or later (GPLv3+)
Classifier: Operating System :: OS Independent
Classifier: Programming Language :: Python :: 3
Classifier: Topic :: Software Development :: Libraries :: Python Modules
Classifier: Topic :: Scientific/Engineering
Requires-Dist: numpy
Requires-Dist: scipy
